bbup/main.py
bbup-1.1.0.dist-info/entry_points.txt
bbup-1.1.0.dist-info/WHEEL
bbup-1.1.0.dist-info/METADATA
bbup-1.1.0.dist-info/RECORD
