Metadata-Version: 2.1
Name: bbup
Version: 1.1.0
Summary: 
Author: Rehmat Alam
Author-email: contact@rehmat.works
Requires-Python: >=3.6,<4.0
Classifier: Programming Language :: Python :: 3
Classifier: Programming Language :: Python :: 3.10
Classifier: Programming Language :: Python :: 3.6
Classifier: Programming Language :: Python :: 3.7
Classifier: Programming Language :: Python :: 3.8
Classifier: Programming Language :: Python :: 3.9
Requires-Dist: b2sdk (>=1.14.0,<2.0.0)
Requires-Dist: colorama (>=0.4.4,<0.5.0)
Requires-Dist: requests (>=2.27.1,<3.0.0)
Requires-Dist: typer[all] (>=0.4.0,<0.5.0)
Requires-Dist: validators (>=0.18.1,<0.19.0)
